MANIFEST.in
README.rst
requirements.txt
setup.py
lisa/__init__.py
lisa/plugins/__init__.py
lisa/plugins/Cinema/README.rst
lisa/plugins/Cinema/__init__.py
lisa/plugins/Cinema/cinema.json
lisa/plugins/Cinema/lang/fr/LC_MESSAGES/cinema.mo
lisa/plugins/Cinema/lang/fr/LC_MESSAGES/cinema.po
lisa/plugins/Cinema/modules/__init__.py
lisa/plugins/Cinema/modules/cinema.py
lisa/plugins/Cinema/web/__init__.py
lisa/plugins/Cinema/web/api.py
lisa/plugins/Cinema/web/models.py
lisa/plugins/Cinema/web/tests.py
lisa/plugins/Cinema/web/urls.py
lisa/plugins/Cinema/web/views.py
lisa_plugin_Cinema.egg-info/PKG-INFO
lisa_plugin_Cinema.egg-info/SOURCES.txt
lisa_plugin_Cinema.egg-info/dependency_links.txt
lisa_plugin_Cinema.egg-info/namespace_packages.txt
lisa_plugin_Cinema.egg-info/requires.txt
lisa_plugin_Cinema.egg-info/top_level.txt