Metadata-Version: 1.1
Name: lisa-plugin-Cinema
Version: 1.0.0
Summary: LISA home automation system - Server
Home-page: http://www.lisa-project.net
Author: Julien Syx
Author-email: julien.syx@gmail.com
License: MIT
Platform: UNKNOWN
Classifier: Development Status :: 4 - Beta
Classifier: Environment :: Console
Classifier: License :: OSI Approved :: MIT License
Classifier: Operating System :: POSIX
Classifier: Programming Language :: Python :: 2
Classifier: Programming Language :: Python :: 2.7
Classifier: Topic :: Internet :: WWW/HTTP
Classifier: Topic :: Software Development :: Libraries :: Python Modules
